README.md
setup.cfg
setup.py
tiramisu_asr/__init__.py
tiramisu_asr.egg-info/PKG-INFO
tiramisu_asr.egg-info/SOURCES.txt
tiramisu_asr.egg-info/dependency_links.txt
tiramisu_asr.egg-info/requires.txt
tiramisu_asr.egg-info/top_level.txt
tiramisu_asr/augmentations/__init__.py
tiramisu_asr/augmentations/augments.py
tiramisu_asr/augmentations/signal_augment.py
tiramisu_asr/augmentations/spec_augment.py
tiramisu_asr/configs/__init__.py
tiramisu_asr/configs/user_config.py
tiramisu_asr/datasets/__init__.py
tiramisu_asr/datasets/asr_dataset.py
tiramisu_asr/datasets/base_dataset.py
tiramisu_asr/featurizers/__init__.py
tiramisu_asr/featurizers/english.txt
tiramisu_asr/featurizers/gammatone.py
tiramisu_asr/featurizers/speech_featurizers.py
tiramisu_asr/featurizers/text_featurizers.py
tiramisu_asr/gradpolicy/__init__.py
tiramisu_asr/gradpolicy/grad_policy.py
tiramisu_asr/gradpolicy/multiview_grad_policy.py
tiramisu_asr/losses/__init__.py
tiramisu_asr/losses/ctc_losses.py
tiramisu_asr/losses/rnnt_losses.py
tiramisu_asr/models/__init__.py
tiramisu_asr/models/activations.py
tiramisu_asr/models/conformer.py
tiramisu_asr/models/ctc.py
tiramisu_asr/models/multiconformers.py
tiramisu_asr/models/transducer.py
tiramisu_asr/models/layers/__init__.py
tiramisu_asr/models/layers/bnlstmcell.py
tiramisu_asr/models/layers/embedding.py
tiramisu_asr/models/layers/merge_two_last_dims.py
tiramisu_asr/models/layers/multihead_attention.py
tiramisu_asr/models/layers/point_wise_ffn.py
tiramisu_asr/models/layers/positional_encoding.py
tiramisu_asr/models/layers/row_conv_1d.py
tiramisu_asr/models/layers/sequence_wise_bn.py
tiramisu_asr/models/layers/subsampling.py
tiramisu_asr/models/layers/time_reduction.py
tiramisu_asr/models/layers/transpose_time_major.py
tiramisu_asr/optimizers/__init__.py
tiramisu_asr/optimizers/schedules.py
tiramisu_asr/runners/__init__.py
tiramisu_asr/runners/base_runners.py
tiramisu_asr/runners/ctc_runners.py
tiramisu_asr/runners/transducer_runners.py
tiramisu_asr/utils/__init__.py
tiramisu_asr/utils/metrics.py
tiramisu_asr/utils/utils.py