Metadata-Version: 2.1
Name: tiramisu-asr
Version: 0.2.3
Summary: Almost State-of-the-art Automatic Speech Recognition using Tensorflow 2
Home-page: https://github.com/usimarit/TiramisuASR
Author: Huy Le Nguyen
Author-email: nlhuy.cs.16@gmail.com
License: UNKNOWN
Platform: UNKNOWN
Classifier: Programming Language :: Python :: 3.6
Classifier: Programming Language :: Python :: 3.7
Classifier: Programming Language :: Python :: 3.8
Classifier: Intended Audience :: Science/Research
Classifier: Operating System :: POSIX :: Linux
Classifier: License :: OSI Approved :: Apache Software License
Classifier: Topic :: Software Development :: Libraries :: Python Modules
Requires-Python: >=3.6
